{
  "blogs": [
    {
      "name": "Thời gian và Động lực",
      "description": "Có lẽ cũng rất lâu rồi mà tôi chưa đụng đến thứ được gọi là “timetable”. Hay dân dã hơn thì người ta hay gọi là “Lịch thường nhật”, còn đối với học sinh, sinh viên gọi là “thời khóa biểu”. Chắc hẳn nhiều người sẽ thắc mắc tại sao tôi là sinh viên mà lại lâu rồi chưa đụng đến cái mà sinh viên đều gọi là thời khóa biểu. Đương nhiên học sinh hay sinh viên đều cần có nó để xem lịch học, để không một buổi sáng nào bị quên mất kiến thức.",
      "createdAt": "",
      "imageUrl": "https://cdn.fullstack.edu.vn/f8-learning/blog_posts/1671/61b6368a3a089.jpg",
      "createdBy": "Dong Ngo",
      "authorAvt": "https://cdn.fullstack.edu.vn/f8-learning/user_avatars/9143/616309bb2f85f.png"
    },
    {
      "name": "Tailwind css và cách cài đặt cơ bản ",
      "description": "Bạn đang lo lắng vì đặt tên class, sợ bị trùng css không mong muốn, hay muốn một framework hỗ trợ css dễ học mà dễ tùy biến theo ý thích đã có tailwind css.",
      "createdAt": "",
      "imageUrl": "https://cdn.fullstack.edu.vn/f8-learning/blog_posts/1653/61b46a3d757cc.png",
      "createdBy": "Quang Trần Anh",
      "authorAvt": "https://lh3.googleusercontent.com/a-/AOh14Gi1WrLyqtS8TzBT4AwgzgT3PDa4DJF6IIzldkM5=s400"
    },
    {
      "name": "Cấu trúc cơ bản trong HTML",
      "description": "xem nhiều tips hay tại kimidev.ga",
      "createdAt": "",
      "imageUrl": "",
      "createdBy": "Tới Xuân",
      "authorAvt": "https://graph.facebook.com/1456025961424217/picture?width=400&height=400"
    },
    {
      "name": "Material UI custom theme với TypeScript",
      "description": "Trường hợp sử dụng, mình muốn add thêm properties color vào Theme để reuse:",
      "createdAt": "",
      "imageUrl": "https://cdn.fullstack.edu.vn/f8-learning/blog_posts/1463/61a1bbd28851c.jpg",
      "createdBy": "Tiep Le",
      "authorAvt": "https://graph.facebook.com/1891289944342922/picture?width=400&height=400"
    }
  ]
}